Metadata-Version: 1.1
Name: django-easy-currencies
Version: 0.2.1
Summary: Simple app to manage currencies conversion in Django using openexchangerates.org service.
Home-page: https://github.com/daveoncode/django-easy-currencies
Author: Davide Zanotti
Author-email: davidezanotti@gmail.com
License: MIT License
Platform: UNKNOWN
Classifier: Environment :: Web Environment
Classifier: Framework :: Django
Classifier: Intended Audience :: Developers
Classifier: License :: OSI Approved :: MIT License
Classifier: Operating System :: OS Independent
Classifier: Programming Language :: Python
Classifier: Programming Language :: Python :: 2.7
Classifier: Programming Language :: Python :: 3
Classifier: Programming Language :: Python :: 3.2
Classifier: Programming Language :: Python :: 3.3
Classifier: Topic :: Internet :: WWW/HTTP
Classifier: Topic :: Internet :: WWW/HTTP :: Dynamic Content
